{
  "schema_version": "scc.skill.v1",
  "skill_id": "combo.ai_ml_and_data_724",
  "version": "1.0.0",
  "owner_role": "workbench_dev",
  "summary": "Expert-level ai_ml_data_integration capabilities for integration in combo contexts",
  "applies_to": {
    "task_class": [
      "*"
    ],
    "tags": [
      "combo",
      "integration",
      "ai_ml_data_integration"
    ]
  },
  "contracts": {
    "input_schema": "contracts/child_task/child_task.schema.json",
    "output_schema": "contracts/submit/submit.schema.json"
  },
  "budgets": {
    "max_loc": 1636,
    "max_files": 41
  },
  "quality_gates": {
    "must_run_allowedTests": true,
    "must_keep_diff_minimal": true
  },
  "enablement": {
    "status": "active",
    "rollout": {
      "mode": "all",
      "percent": 100
    }
  },
  "metadata": {
    "category": "combo",
    "subcategory": "integration",
    "tags": [
      "combo",
      "integration",
      "ai_ml_data_integration",
      "imported",
      "community"
    ],
    "complexity": "intermediate",
    "imported_at": "2026-02-09T20:39:53.377Z",
    "popularity_score": 16
  }
}
